<?xml version="1.0" encoding="utf-8" ?>
<elements>
	<info>
		<update version="0.0.3">
			<file name="sources.xml" url="https://raw.githubusercontent.com/mazetree/Aurora-Files/main/source.xml" />
		</update>
	</info>
	<element name="Dhurn Toldur" type="Source" source="Core" id="ID_HOMEBREW_SOURCE_DHURN_TOLDUR">
		<description>
			<p>Player items and mounts for the Dhurn Toldur campaign</p>
		</description>
		<setters>
			<set name="abbreviation">DHTD</set>
			<set name="image">https://yt3.googleusercontent.com/Uv2vfoAVNEjg2t9ZsOMW5bcLEKk3PEdEOFmQSGVPhg_s6lvS4rnut4omrxPcUXbjZCMOrQ4WlQ=s176-c-k-c0x00ffffff-no-rj</set>
			<set name="url">https://twitter.com/mazetree_</set>
			<set name="author" abbreviation="MAZE" url="https://twitter.com/mazetree_">Maze Tree</set>
			<set name="release">20230221</set>
			<set name="playtest">true</set>
			<set name="homebrew">true</set>
		</setters>
	</element>
</elements>
